xcalibrate/__init__.py
xcalibrate/test.py
xcalibrate-0.0.1.dist-info/LICENSE
xcalibrate-0.0.1.dist-info/METADATA
xcalibrate-0.0.1.dist-info/WHEEL
xcalibrate-0.0.1.dist-info/top_level.txt
xcalibrate-0.0.1.dist-info/RECORD
