Metadata-Version: 2.1
Name: xcalibrate
Version: 0.0.1
Summary: Bayesian algorithm for radiometer calibration
Author-email: Ian Roque <laurent.roque@yahoo.com>
Project-URL: Homepage, https://github.com/laurentroque/xcalibrate
Classifier: Programming Language :: Python :: 3
Classifier: Operating System :: OS Independent
Requires-Python: >=3.7
License-File: LICENSE
